datasets_bleu-0.2.dist-info/DESCRIPTION.rst
datasets_bleu-0.2.dist-info/METADATA
datasets_bleu-0.2.dist-info/RECORD
datasets_bleu-0.2.dist-info/WHEEL
datasets_bleu-0.2.dist-info/metadata.json
datasets_bleu-0.2.dist-info/top_level.txt
datasetsbleu/__init__.py
datasetsbleu/app_main.py
datasetsbleu/main.py
datasetsbleu/bleu_calc/__init__.py
datasetsbleu/bleu_calc/binarizer.py
datasetsbleu/bleu_calc/bleu.py
datasetsbleu/bleu_calc/data_utils.py
datasetsbleu/bleu_calc/dictionary.py
datasetsbleu/bleu_calc/file_io.py
datasetsbleu/bleu_calc/score.py
datasetsbleu/bleu_calc/tokenizer.py
datasetsbleu/engine/__init__.py
datasetsbleu/engine/bleu_level_2file.py
datasetsbleu/engine/bleu_level_en_zh.py
datasetsbleu/engine/en_zh.py
datasetsbleu/engine/en_zh_2file.py
datasetsbleu/engine/engine_run.py
datasetsbleu/utils/__init__.py
datasetsbleu/utils/scripts.py
datasetsbleu/utils/youdao.py
