Metadata-Version: 2.0
Name: datasets-bleu
Version: 0.2
Summary: UNKNOWN
Home-page: https://github.com/
Author: Spider
Author-email: 18128872727@163.com
License: MIT
Platform: UNKNOWN
Classifier: License :: OSI Approved :: MIT License
Classifier: Operating System :: OS Independent
Classifier: Natural Language :: Chinese (Simplified)
Classifier: Programming Language :: Python :: 3
Requires-Dist: Faker
Requires-Dist: tenacity
